{
  "brand_and_full_name": "OnePlus 7 Pro 128GB 6GB RAM",
  "Design": {
    "weight_g": 206.0,
    "thickness_mm": 8.8,
    "width_mm": 76.0,
    "height_mm": 162.6,
    "IP_rating": null,
    "volume_cm3": 108.75
  },
  "Screen": {
    "screen_size_in": 6.67,
    "screen_type": "OLED/AMOLED",
    "pixel_density_ppi": 516.0,
    "resolution": "1440 x 3120 px",
    "refresh_rate_hz": 90.0,
    "typical_brightness_nits": null,
    "HDR10_compatible": false,
    "Dolby_Vision_compatible": false
  },
  "Performance": {
    "storage_options_gb": 128.0,
    "RAM_gb": 6.0,
    "AnTuTu_benchmark_score": 447375.0,
    "GPU_name": "Adreno 640OnePlus 7 Pro (128GB / 6GB RAM)",
    "processor_speed_ghz": {
      "text": "1 x 2.84 GHz & 3 x 2.42 GHz & 4 x 1.8 GHz",
      "value": 17.3
    },
    "RAM_speed_mhz": 2133.0,
    "semiconductor_size_nm": 7.0,
    "supports_64_bit": true,
    "uses_big_LITTLE_technology": true,
    "processor_threads": 8.0,
    "uses_multithreading": false
  },
  "Cameras": {
    "main_camera_megapixels": {
      "text": "48 MP & 16 MP & 8 MP",
      "value": 72.0
    },
    "front_camera_megapixels": 16.0,
    "built_in_optical_image_stabilization": true,
    "video_recording": "2160 x 60 fps",
    "largest_aperture_f": 1.6,
    "continuous_autofocus_during_video_recording": true,
    "can_record_slow_motion_videos": true,
    "HDR_mode": true,
    "optical_zoom_x": 3.0,
    "CMOS_sensor": true,
    "manual_ISO": true,
    "burst_mode": true,
    "manual_focus": true,
    "manual_white_balance": true,
    "takes_raw_images": true,
    "AF_touch": true,
    "manual_shutter_speed": false,
    "large_aperture_front_camera_f": 2.0,
    "Dolby_Vision_recording": false
  },
  "Operating_System": {
    "version": "Android 9 Pie",
    "location_privacy_options": false,
    "camera_and_microphone_privacy_options": false,
    "theme_customization": true,
    "dark_mode": false,
    "WiFi_password_sharing": false,
    "battery_health_check": false,
    "extra_dim_mode": false,
    "Focus_mode": false,
    "dynamic_theming": false,
    "offload_apps": false,
    "customizable_notifications": true,
    "live_text": false,
    "direct_OS_updates": false,
    "quick_start": false
  },
  "Battery": {
    "battery_capacity_mAh": 4000.0,
    "wireless_charging": false,
    "fast_charging": true,
    "charging_speed_w": 30.0,
    "battery_life_h": null
  },
  "Audio": {
    "built_in_stereo_speaker": true,
    "aptX": true,
    "LDAC": false,
    "aptX_HD": true
  },
  "Features": {
    "supports_5G": true,
    "WiFi_version": "Wi-Fi 5 (802.11ac), Wi-Fi 4 (802.11n)",
    "download_speed_mbps": 1200.0,
    "upload_speed_mbps": 150.0,
    "USB_Type_C_ports": true,
    "USB_version": "3.1",
    "NFC_device": true,
    "SIM_cards": "2 SIM",
    "fingerprint_reader": true,
    "emergency_communication_via_satellite": false,
    "detects_car_accidents": false,
    "Bluetooth_version": "5",
    "gyroscope": true,
    "GPS": true,
    "compass": true,
    "WiFi_compatible": true,
    "infrared_sensor": false,
    "accelerometer": true,
    "barometer": false,
    "supports_Galileo": true
  }
}